zodable_idschema/__init__.py
zodable_idschema/isdchema.py
zodable_idschema/py.typed
zodable_idschema-1.0.5.dist-info/METADATA
zodable_idschema-1.0.5.dist-info/WHEEL
zodable_idschema-1.0.5.dist-info/top_level.txt
zodable_idschema-1.0.5.dist-info/RECORD
